setup.py
bin/pagerunit
pagerunit/__init__.py
pagerunit/decorators.py
pagerunit/smtp.py
pagerunit.egg-info/PKG-INFO
pagerunit.egg-info/SOURCES.txt
pagerunit.egg-info/dependency_links.txt
pagerunit.egg-info/not-zip-safe
pagerunit.egg-info/top_level.txt