Metadata-Version: 1.0
Name: pagerunit
Version: 0.0.3
Summary: A simple Nagios alternative made to look like unit tests.
Home-page: https://github.com/rcrowley/pagerunit
Author: Richard Crowley
Author-email: r@rcrowley.org
License: BSD
Platform: UNKNOWN
